MANIFEST.in
README.rst
setup.py
graphics/Icon.gif
src/gEEProg.py
src/gEEProgGUI
src/gEEProg.egg-info/PKG-INFO
src/gEEProg.egg-info/SOURCES.txt
src/gEEProg.egg-info/dependency_links.txt
src/gEEProg.egg-info/requires.txt
src/gEEProg.egg-info/top_level.txt