Metadata-Version: 1.0
Name: gEEProg
Version: 2.0.1
Summary: GUI to control D'Asaro Designs EEPROM programmers.
Home-page: http://www.dasarodesigns.com/
Author: Mark Chilenski
Author-email: mark.chilenski@gmail.com
License: GPL
Platform: UNKNOWN
